<?xml version="1.0" encoding="utf-8"?>
<Suppressions xmlns:xsi="http://www.w3.org/2001/XMLSchema-instance" xmlns:xsd="http://www.w3.org/2001/XMLSchema">
  <Suppression>
    <DiagnosticId>CP0002</DiagnosticId>
    <Target>M:Smdn.Xml.Linq.Extensions.GetAttributeValue``1(System.Xml.Linq.XElement,System.Xml.Linq.XName,System.Func{System.String,``0})</Target>
    <Left>lib/netstandard1.6/Smdn.Fundamental.Xml.Linq.dll</Left>
    <Right>lib/netstandard2.0/Smdn.Fundamental.Xml.Linq.dll</Right>
  </Suppression>
</Suppressions>
